mcp_server_openai/__init__.py
mcp_server_openai/llm.py
mcp_server_openai/server.py
mcp_server_openai/test_openai.py
iflow_mcp_mcp_server_openai-0.1.0.dist-info/METADATA
iflow_mcp_mcp_server_openai-0.1.0.dist-info/WHEEL
iflow_mcp_mcp_server_openai-0.1.0.dist-info/entry_points.txt
iflow_mcp_mcp_server_openai-0.1.0.dist-info/licenses/LICENSE
iflow_mcp_mcp_server_openai-0.1.0.dist-info/RECORD
