Metadata-Version: 2.4
Name: iflow-mcp_mcp-server-openai
Version: 0.1.0
Summary: MCP server for OpenAI API integration
License-File: LICENSE
Requires-Python: >=3.10
Requires-Dist: click>=8.0.0
Requires-Dist: mcp>=0.9.1
Requires-Dist: openai>=1.0.0
Requires-Dist: pytest-asyncio
